{
"id":"C401", 
"services":[
{"name":"algorithm","alternatives":["diksjtra"]}
, {"name":"weighting","alternatives":["least_noisy", "fastest", "shortest"]}
, {"name":"vehicle","alternatives":["car"]}
]
,
"platforms":[
{
"id":"S259", 
"host":"http://e105m01.istic.univ-rennes1.fr:1539/",
"services":[
{"name":"algorithm","alternatives":["diksjtra"]}
, {"name":"weighting","alternatives":["least_noisy", "fastest", "shortest", "default"]}
, {"name":"vehicle","alternatives":["car", "foot", "bike"]}
]
}
, {
"id":"S574", 
"host":"http://d024m06.istic.univ-rennes1.fr:1533/",
"services":[
{"name":"algorithm","alternatives":["diksjtra"]}
, {"name":"weighting","alternatives":["default", "fastest", "least_noisy", "shortest"]}
, {"name":"vehicle","alternatives":["car", "foot", "bike"]}
]
}
, {
"id":"S683", 
"host":"http://d028m04.istic.univ-rennes1.fr:15310/",
"services":[
{"name":"algorithm","alternatives":["diksjtra"]}
, {"name":"weighting","alternatives":["fastest", "least_noisy", "default", "shortest"]}
, {"name":"vehicle","alternatives":["car", "bike"]}
]
}
]
}

