{
"id":"C154", 
"services":[
{"name":"algorithm","alternatives":["diksjtra"]}
, {"name":"weighting","alternatives":["shortest"]}
, {"name":"vehicle","alternatives":["car", "bike", "foot", "motorcycle", "scooter"]}
]
,
"platforms":[
{
"id":"S120", 
"host":"http://e103m04.istic.univ-rennes1.fr:15310/",
"services":[
{"name":"algorithm","alternatives":["diksjtra"]}
, {"name":"weighting","alternatives":["default", "shortest", "least_noisy", "least_congested", "fastest"]}
, {"name":"vehicle","alternatives":["car", "bike", "foot", "motorcycle", "scooter"]}
]
}
]
}

