{
"id":"C974", 
"services":[
{"name":"algorithm","alternatives":["diksjtra"]}
, {"name":"weighting","alternatives":["default", "fastest"]}
, {"name":"vehicle","alternatives":["car", "motorcycle"]}
]
,
"platforms":[
{
"id":"S142", 
"host":"http://e103m07.istic.univ-rennes1.fr:1532/",
"services":[
{"name":"algorithm","alternatives":["diksjtra"]}
, {"name":"weighting","alternatives":["fastest", "least_congested", "shortest", "default", "least_polluted"]}
, {"name":"vehicle","alternatives":["motorcycle", "car"]}
]
}
, {
"id":"S243", 
"host":"http://e008m10.istic.univ-rennes1.fr:1533/",
"services":[
{"name":"algorithm","alternatives":["diksjtra"]}
, {"name":"weighting","alternatives":["fastest", "default", "least_noisy", "least_congested"]}
, {"name":"vehicle","alternatives":["bike", "car", "motorcycle"]}
]
}
, {
"id":"S103", 
"host":"http://e103m02.istic.univ-rennes1.fr:1533/",
"services":[
{"name":"algorithm","alternatives":["diksjtra"]}
, {"name":"weighting","alternatives":["least_congested", "default", "fastest"]}
, {"name":"vehicle","alternatives":["car", "motorcycle", "foot"]}
]
}
]
}

