{
"id":"C3721", 
"services":[
{"name":"algorithm","alternatives":["diksjtra"]}
, {"name":"weighting","alternatives":["fastest"]}
, {"name":"vehicle","alternatives":["car", "foot"]}
]
,
"platforms":[
{
"id":"S418", 
"host":"http://e212m08.istic.univ-rennes1.fr:1538/",
"services":[
{"name":"algorithm","alternatives":["diksjtra"]}
, {"name":"weighting","alternatives":["fastest", "default"]}
, {"name":"vehicle","alternatives":["car", "foot", "bike"]}
]
}
, {
"id":"S387", 
"host":"http://e212m04.istic.univ-rennes1.fr:1537/",
"services":[
{"name":"algorithm","alternatives":["diksjtra"]}
, {"name":"weighting","alternatives":["default", "fastest", "least_noisy", "shortest"]}
, {"name":"vehicle","alternatives":["car", "foot"]}
]
}
]
}

