{
"id":"C4392", 
"services":[
{"name":"algorithm","alternatives":["diksjtra"]}
, {"name":"weighting","alternatives":["default"]}
, {"name":"vehicle","alternatives":["car", "bike"]}
]
,
"platforms":[
{
"id":"S229", 
"host":"http://e008m08.istic.univ-rennes1.fr:1539/",
"services":[
{"name":"algorithm","alternatives":["diksjtra"]}
, {"name":"weighting","alternatives":["fastest", "default", "shortest"]}
, {"name":"vehicle","alternatives":["bike", "car"]}
]
}
, {
"id":"S604", 
"host":"http://d026m02.istic.univ-rennes1.fr:1531/",
"services":[
{"name":"algorithm","alternatives":["diksjtra"]}
, {"name":"weighting","alternatives":["fastest", "shortest", "most_scenic", "default"]}
, {"name":"vehicle","alternatives":["bike", "car"]}
]
}
]
}

