{
"id":"C3935", 
"services":[
{"name":"algorithm","alternatives":["diksjtra"]}
, {"name":"weighting","alternatives":["least_congested", "fastest"]}
, {"name":"vehicle","alternatives":["car", "bike"]}
]
,
"platforms":[
{
"id":"S434", 
"host":"http://d020m01.istic.univ-rennes1.fr:1534/",
"services":[
{"name":"algorithm","alternatives":["diksjtra"]}
, {"name":"weighting","alternatives":["default", "least_noisy", "least_congested", "shortest"]}
, {"name":"vehicle","alternatives":["bike", "car"]}
]
}
, {
"id":"S109", 
"host":"http://e103m02.istic.univ-rennes1.fr:1539/",
"services":[
{"name":"algorithm","alternatives":["diksjtra"]}
, {"name":"weighting","alternatives":["fastest", "default", "shortest", "least_congested", "least_polluted"]}
, {"name":"vehicle","alternatives":["car", "bike"]}
]
}
, {
"id":"S439", 
"host":"http://d020m01.istic.univ-rennes1.fr:1539/",
"services":[
{"name":"algorithm","alternatives":["diksjtra"]}
, {"name":"weighting","alternatives":["shortest", "fastest", "least_congested"]}
, {"name":"vehicle","alternatives":["car", "bike"]}
]
}
, {
"id":"S281", 
"host":"http://e105m04.istic.univ-rennes1.fr:1531/",
"services":[
{"name":"algorithm","alternatives":["diksjtra"]}
, {"name":"weighting","alternatives":["default", "least_congested", "fastest"]}
, {"name":"vehicle","alternatives":["car", "bike"]}
]
}
, {
"id":"S546", 
"host":"http://d024m01.istic.univ-rennes1.fr:1531/",
"services":[
{"name":"algorithm","alternatives":["diksjtra"]}
, {"name":"weighting","alternatives":["least_congested", "default", "fastest", "least_polluted", "least_noisy", "shortest", "least_pollen"]}
, {"name":"vehicle","alternatives":["car", "motorcycle", "bike"]}
]
}
, {
"id":"S21", 
"host":"http://e003m04.istic.univ-rennes1.fr:1531/",
"services":[
{"name":"algorithm","alternatives":["diksjtra"]}
, {"name":"weighting","alternatives":["fastest"]}
, {"name":"vehicle","alternatives":["car", "bike"]}
]
}
]
}

