{
"id":"C777", 
"services":[
{"name":"algorithm","alternatives":["dijkstra"]}
, {"name":"vehicle","alternatives":["car", "foot", "motorcycle"]}
, {"name":"weighting","alternatives":["fastest", "least_congested"]}
]
,
"platforms":[
{
"id":"S166", 
"host":"http://e103m07.istic.univ-rennes1.fr:1532/",
"services":[
{"name":"algorithm","alternatives":["dijkstra"]}
, {"name":"vehicle","alternatives":["car", "foot", "motorcycle", "bike"]}
, {"name":"weighting","alternatives":["fastest", "least_congested", "least_polluted", "default"]}
]
}
, {
"id":"S718", 
"host":"http://d026m04.istic.univ-rennes1.fr:1535/",
"services":[
{"name":"algorithm","alternatives":["dijkstra"]}
, {"name":"vehicle","alternatives":["car", "bike"]}
, {"name":"weighting","alternatives":["default", "fastest", "least_congested"]}
]
}
]
}

