{
"id":"C1565", 
"services":[
{"name":"algorithm","alternatives":["dijkstra"]}
, {"name":"vehicle","alternatives":["car", "bike"]}
, {"name":"weighting","alternatives":["least_congested", "least_noisy"]}
]
,
"platforms":[
{
"id":"S725", 
"host":"http://d026m05.istic.univ-rennes1.fr:1532/",
"services":[
{"name":"algorithm","alternatives":["dijkstra"]}
, {"name":"vehicle","alternatives":["car", "scooter", "bike", "foot"]}
, {"name":"weighting","alternatives":["fastest", "least_noisy", "default", "least_congested"]}
]
}
, {
"id":"S683", 
"host":"http://d024m10.istic.univ-rennes1.fr:1535/",
"services":[
{"name":"algorithm","alternatives":["dijkstra"]}
, {"name":"vehicle","alternatives":["car"]}
, {"name":"weighting","alternatives":["least_congested", "least_noisy"]}
]
}
]
}

