{
"id":"C749", 
"services":[
{"name":"algorithm","alternatives":["dijkstra"]}
, {"name":"vehicle","alternatives":["foot"]}
, {"name":"weighting","alternatives":["default", "shortest", "fastest", "least_noisy"]}
]
,
"platforms":[
{
"id":"S714", 
"host":"http://d026m04.istic.univ-rennes1.fr:1531/",
"services":[
{"name":"algorithm","alternatives":["dijkstra"]}
, {"name":"vehicle","alternatives":["car", "motorcycle", "foot"]}
, {"name":"weighting","alternatives":["default", "fastest", "least_congested", "least_noisy", "shortest"]}
]
}
]
}

