{
"id":"C348", 
"services":[
{"name":"algorithm","alternatives":["dijkstra"]}
, {"name":"vehicle","alternatives":["foot"]}
, {"name":"weighting","alternatives":["fastest", "least_congested"]}
]
,
"platforms":[
{
"id":"S160", 
"host":"http://e103m08.istic.univ-rennes1.fr:1538/",
"services":[
{"name":"algorithm","alternatives":["dijkstra"]}
, {"name":"vehicle","alternatives":["bike", "car", "foot", "motorcycle"]}
, {"name":"weighting","alternatives":["fastest", "default", "shortest", "least_congested"]}
]
}
, {
"id":"S18", 
"host":"http://e003m02.istic.univ-rennes1.fr:1538/",
"services":[
{"name":"algorithm","alternatives":["dijkstra"]}
, {"name":"vehicle","alternatives":["car", "bike", "foot"]}
, {"name":"weighting","alternatives":["least_polluted", "least_congested", "fastest", "default"]}
]
}
]
}

