{
"id":"C474", 
"services":[
{"name":"algorithm","alternatives":["dijkstra"]}
, {"name":"vehicle","alternatives":["car", "foot"]}
, {"name":"weighting","alternatives":["least_polluted", "default"]}
]
,
"platforms":[
{
"id":"S167", 
"host":"http://e103m09.istic.univ-rennes1.fr:1535/",
"services":[
{"name":"algorithm","alternatives":["dijkstra"]}
, {"name":"vehicle","alternatives":["car", "foot"]}
, {"name":"weighting","alternatives":["fastest", "default", "least_congested", "least_pollen", "shortest", "least_noisy", "least_polluted"]}
]
}
, {
"id":"S206", 
"host":"http://e008m06.istic.univ-rennes1.fr:1534/",
"services":[
{"name":"algorithm","alternatives":["dijkstra"]}
, {"name":"vehicle","alternatives":["car", "foot"]}
, {"name":"weighting","alternatives":["default", "least_polluted"]}
]
}
, {
"id":"S155", 
"host":"http://e103m08.istic.univ-rennes1.fr:1534/",
"services":[
{"name":"algorithm","alternatives":["dijkstra"]}
, {"name":"vehicle","alternatives":["car", "foot", "motorcycle"]}
, {"name":"weighting","alternatives":["shortest", "least_congested", "fastest", "least_noisy", "most_scenic", "default", "least_polluted"]}
]
}
, {
"id":"S215", 
"host":"http://e008m07.istic.univ-rennes1.fr:1533/",
"services":[
{"name":"algorithm","alternatives":["dijkstra"]}
, {"name":"vehicle","alternatives":["car", "motorcycle", "bike", "foot", "scooter"]}
, {"name":"weighting","alternatives":["least_noisy", "default", "least_congested", "least_polluted", "fastest"]}
]
}
]
}

