{
"id":"C187", 
"services":[
{"name":"algorithm","alternatives":["dijkstra"]}
, {"name":"vehicle","alternatives":["motorcycle"]}
, {"name":"weighting","alternatives":["fastest", "least_pollen", "shortest", "default"]}
]
,
"platforms":[
{
"id":"S172", 
"host":"http://e103m09.istic.univ-rennes1.fr:15310/",
"services":[
{"name":"algorithm","alternatives":["dijkstra"]}
, {"name":"vehicle","alternatives":["car", "motorcycle", "bike", "foot"]}
, {"name":"weighting","alternatives":["default", "fastest", "shortest", "least_pollen", "least_congested"]}
]
}
]
}

