{
"id":"C4152", 
"services":[
{"name":"algorithm","alternatives":["astar"]}
, {"name":"weighting","alternatives":["shortest", "fastest"]}
, {"name":"vehicle","alternatives":["bike", "car"]}
]
,
"platforms":[
{
"id":"S731", 
"host":"http://d122m01.istic.univ-rennes1.fr:1538/",
"services":[
{"name":"algorithm","alternatives":["astar"]}
, {"name":"weighting","alternatives":["least_congested", "default", "shortest", "least_noisy", "fastest", "least_polluted"]}
, {"name":"vehicle","alternatives":["car", "bike", "foot"]}
]
}
, {
"id":"S543", 
"host":"http://d022m10.istic.univ-rennes1.fr:1538/",
"services":[
{"name":"algorithm","alternatives":["astar"]}
, {"name":"weighting","alternatives":["default", "fastest", "least_congested", "shortest"]}
, {"name":"vehicle","alternatives":["car", "foot", "bike"]}
]
}
, {
"id":"S163", 
"host":"http://e103m09.istic.univ-rennes1.fr:1533/",
"services":[
{"name":"algorithm","alternatives":["astar"]}
, {"name":"weighting","alternatives":["default", "fastest", "least_noisy", "least_congested", "least_pollen"]}
, {"name":"vehicle","alternatives":["car", "bike"]}
]
}
]
}

