{
"id":"C1090", 
"services":[
{"name":"algorithm","alternatives":["diksjtra"]}
, {"name":"weighting","alternatives":["shortest"]}
, {"name":"vehicle","alternatives":["car", "foot"]}
]
,
"platforms":[
{
"id":"S86", 
"host":"http://e003m10.istic.univ-rennes1.fr:1536/",
"services":[
{"name":"algorithm","alternatives":["diksjtra"]}
, {"name":"weighting","alternatives":["default", "fastest", "shortest", "most_ozonic", "least_noisy", "least_congested"]}
, {"name":"vehicle","alternatives":["motorcycle", "car", "foot"]}
]
}
, {
"id":"S314", 
"host":"http://e105m07.istic.univ-rennes1.fr:1534/",
"services":[
{"name":"algorithm","alternatives":["diksjtra"]}
, {"name":"weighting","alternatives":["shortest"]}
, {"name":"vehicle","alternatives":["foot"]}
]
}
]
}

