{
"id":"C210", 
"services":[
{"name":"vehicle","alternatives":["bike", "foot", "car"]}
, {"name":"weighting","alternatives":["shortest"]}
, {"name":"algorithm","alternatives":["dijkstra"]}
]
,
"platforms":[
{
"id":"S237", 
"host":"http://e008m09.istic.univ-rennes1.fr:1535/",
"services":[
{"name":"vehicle","alternatives":["car", "foot", "bike"]}
, {"name":"weighting","alternatives":["default", "fastest", "shortest", "least_congested", "least_polluted", "most_scenic"]}
, {"name":"algorithm","alternatives":["dijkstra"]}
]
}
, {
"id":"S42", 
"host":"http://e003m05.istic.univ-rennes1.fr:15310/",
"services":[
{"name":"vehicle","alternatives":["car", "foot", "bike", "motorcycle", "scooter"]}
, {"name":"weighting","alternatives":["shortest", "least_noisy", "default", "least_congested", "fastest", "least_polluted", "least_pollen"]}
, {"name":"algorithm","alternatives":["dijkstra"]}
]
}
, {
"id":"S489", 
"host":"http://d020m10.istic.univ-rennes1.fr:1534/",
"services":[
{"name":"vehicle","alternatives":["bike", "foot"]}
, {"name":"weighting","alternatives":["least_polluted", "shortest", "most_scenic"]}
, {"name":"algorithm","alternatives":["dijkstra"]}
]
}
, {
"id":"S612", 
"host":"http://d026m02.istic.univ-rennes1.fr:1537/",
"services":[
{"name":"vehicle","alternatives":["car", "motorcycle"]}
, {"name":"weighting","alternatives":["fastest", "shortest", "most_ozonic", "least_pollen", "least_congested"]}
, {"name":"algorithm","alternatives":["dijkstra"]}
]
}
]
}

