{
"id":"C3203", 
"services":[
{"name":"vehicle","alternatives":["bike"]}
, {"name":"weighting","alternatives":["fastest", "least_noisy"]}
, {"name":"algorithm","alternatives":["astar"]}
]
,
"platforms":[
{
"id":"S734", 
"host":"http://d122m01.istic.univ-rennes1.fr:1539/",
"services":[
{"name":"vehicle","alternatives":["car", "foot", "bike"]}
, {"name":"weighting","alternatives":["shortest", "fastest", "least_congested", "default", "least_noisy", "least_polluted", "most_ozonic"]}
, {"name":"algorithm","alternatives":["astar"]}
]
}
, {
"id":"S536", 
"host":"http://d022m08.istic.univ-rennes1.fr:1536/",
"services":[
{"name":"vehicle","alternatives":["car", "foot", "bike", "motorcycle"]}
, {"name":"weighting","alternatives":["default", "fastest", "most_scenic", "least_congested", "shortest", "least_polluted"]}
, {"name":"algorithm","alternatives":["astar"]}
]
}
]
}

