{
"id":"C944", 
"services":[
{"name":"algorithm","alternatives":["dijkstra"]}
, {"name":"vehicle","alternatives":["car", "foot"]}
, {"name":"weighting","alternatives":["least_congested", "default", "fastest"]}
]
,
"platforms":[
{
"id":"S217", 
"host":"http://e008m07.istic.univ-rennes1.fr:1535/",
"services":[
{"name":"algorithm","alternatives":["dijkstra"]}
, {"name":"vehicle","alternatives":["car", "bike", "foot", "scooter", "motorcycle"]}
, {"name":"weighting","alternatives":["fastest", "least_congested", "default", "least_polluted"]}
]
}
, {
"id":"S122", 
"host":"http://e103m05.istic.univ-rennes1.fr:1531/",
"services":[
{"name":"algorithm","alternatives":["dijkstra"]}
, {"name":"vehicle","alternatives":["car", "bike", "foot", "motorcycle"]}
, {"name":"weighting","alternatives":["fastest", "least_congested", "default"]}
]
}
, {
"id":"S200", 
"host":"http://e008m05.istic.univ-rennes1.fr:1538/",
"services":[
{"name":"algorithm","alternatives":["dijkstra"]}
, {"name":"vehicle","alternatives":["car", "foot", "bike"]}
, {"name":"weighting","alternatives":["default", "fastest", "shortest", "least_congested", "least_polluted", "least_noisy"]}
]
}
, {
"id":"S129", 
"host":"http://e103m05.istic.univ-rennes1.fr:1538/",
"services":[
{"name":"algorithm","alternatives":["dijkstra"]}
, {"name":"vehicle","alternatives":["car", "foot", "bike"]}
, {"name":"weighting","alternatives":["fastest", "least_noisy", "shortest", "default", "least_congested"]}
]
}
]
}

