{
"id":"C1779", 
"services":[
{"name":"algorithm","alternatives":["dijkstra"]}
, {"name":"vehicle","alternatives":["car", "bike", "foot"]}
, {"name":"weighting","alternatives":["least_polluted", "default"]}
]
,
"platforms":[
{
"id":"S74", 
"host":"http://e003m08.istic.univ-rennes1.fr:1534/",
"services":[
{"name":"algorithm","alternatives":["dijkstra"]}
, {"name":"vehicle","alternatives":["car", "bike", "foot"]}
, {"name":"weighting","alternatives":["shortest", "default", "least_polluted", "fastest", "least_congested"]}
]
}
, {
"id":"S646", 
"host":"http://d024m03.istic.univ-rennes1.fr:1535/",
"services":[
{"name":"algorithm","alternatives":["dijkstra"]}
, {"name":"vehicle","alternatives":["car"]}
, {"name":"weighting","alternatives":["default", "least_polluted", "least_noisy", "fastest"]}
]
}
]
}

