{
"id":"C396", 
"services":[
{"name":"algorithm","alternatives":["dijkstra"]}
, {"name":"vehicle","alternatives":["car"]}
, {"name":"weighting","alternatives":["default", "fastest"]}
]
,
"platforms":[
{
"id":"S112", 
"host":"http://e103m04.istic.univ-rennes1.fr:1531/",
"services":[
{"name":"algorithm","alternatives":["dijkstra"]}
, {"name":"vehicle","alternatives":["car", "foot", "bike", "motorcycle"]}
, {"name":"weighting","alternatives":["default", "fastest", "least_congested", "least_noisy", "least_pollen"]}
]
}
, {
"id":"S68", 
"host":"http://e003m08.istic.univ-rennes1.fr:1538/",
"services":[
{"name":"algorithm","alternatives":["dijkstra"]}
, {"name":"vehicle","alternatives":["car"]}
, {"name":"weighting","alternatives":["fastest", "least_noisy", "least_congested", "least_pollen", "default", "shortest", "least_polluted"]}
]
}
, {
"id":"S146", 
"host":"http://e103m07.istic.univ-rennes1.fr:1535/",
"services":[
{"name":"algorithm","alternatives":["dijkstra"]}
, {"name":"vehicle","alternatives":["car", "bike"]}
, {"name":"weighting","alternatives":["fastest", "default", "least_congested", "least_polluted"]}
]
}
, {
"id":"S164", 
"host":"http://e103m09.istic.univ-rennes1.fr:1532/",
"services":[
{"name":"algorithm","alternatives":["dijkstra"]}
, {"name":"vehicle","alternatives":["foot", "car", "bike", "motorcycle"]}
, {"name":"weighting","alternatives":["fastest", "default", "shortest", "least_congested", "least_pollen", "least_polluted"]}
]
}
, {
"id":"S170", 
"host":"http://e103m09.istic.univ-rennes1.fr:1538/",
"services":[
{"name":"algorithm","alternatives":["dijkstra"]}
, {"name":"vehicle","alternatives":["car", "bike", "motorcycle"]}
, {"name":"weighting","alternatives":["fastest", "default", "least_congested", "least_noisy", "shortest", "most_ozonic"]}
]
}
, {
"id":"S63", 
"host":"http://e003m08.istic.univ-rennes1.fr:1533/",
"services":[
{"name":"algorithm","alternatives":["dijkstra"]}
, {"name":"vehicle","alternatives":["car", "bike"]}
, {"name":"weighting","alternatives":["fastest", "most_scenic"]}
]
}
]
}

