{
"id":"C688", 
"services":[
{"name":"algorithm","alternatives":["dijkstra"]}
, {"name":"vehicle","alternatives":["foot"]}
, {"name":"weighting","alternatives":["default", "fastest"]}
]
,
"platforms":[
{
"id":"S200", 
"host":"http://e008m05.istic.univ-rennes1.fr:1538/",
"services":[
{"name":"algorithm","alternatives":["dijkstra"]}
, {"name":"vehicle","alternatives":["foot", "bike", "motorcycle"]}
, {"name":"weighting","alternatives":["least_polluted", "least_congested", "fastest", "default"]}
]
}
, {
"id":"S226", 
"host":"http://e008m08.istic.univ-rennes1.fr:1534/",
"services":[
{"name":"algorithm","alternatives":["dijkstra"]}
, {"name":"vehicle","alternatives":["car", "scooter", "foot", "motorcycle", "bike"]}
, {"name":"weighting","alternatives":["default", "shortest", "least_congested", "least_noisy"]}
]
}
]
}

