{
"id":"C2606", 
"services":[
{"name":"vehicle","alternatives":["bike"]}
, {"name":"weighting","alternatives":["least_congested", "fastest", "default"]}
, {"name":"algorithm","alternatives":["dijkstra"]}
]
,
"platforms":[
{
"id":"S690", 
"host":"http://d028m05.istic.univ-rennes1.fr:1535/",
"services":[
{"name":"vehicle","alternatives":["bike"]}
, {"name":"weighting","alternatives":["default", "shortest", "fastest"]}
, {"name":"algorithm","alternatives":["dijkstra"]}
]
}
, {
"id":"S837", 
"host":"http://null/",
"services":[
{"name":"vehicle","alternatives":["bike"]}
, {"name":"weighting","alternatives":["fastest", "default", "least_congested", "shortest", "least_noisy"]}
, {"name":"algorithm","alternatives":["dijkstra"]}
]
}
]
}

