{
"id":"C1752", 
"services":[
{"name":"vehicle","alternatives":["car"]}
, {"name":"weighting","alternatives":["default", "fastest", "most_ozonic", "least_congested"]}
, {"name":"algorithm","alternatives":["dijkstra"]}
]
,
"platforms":[
{
"id":"S650", 
"host":"http://d026m06.istic.univ-rennes1.fr:1535/",
"services":[
{"name":"vehicle","alternatives":["car", "bike"]}
, {"name":"weighting","alternatives":["default", "fastest", "shortest", "least_noisy", "least_congested"]}
, {"name":"algorithm","alternatives":["dijkstra"]}
]
}
, {
"id":"S574", 
"host":"http://d024m05.istic.univ-rennes1.fr:1534/",
"services":[
{"name":"vehicle","alternatives":["car"]}
, {"name":"weighting","alternatives":["fastest", "least_congested", "shortest", "default", "least_polluted", "least_noisy", "most_ozonic"]}
, {"name":"algorithm","alternatives":["dijkstra"]}
]
}
]
}

