{
"id":"C233", 
"services":[
{"name":"weighting","alternatives":["least_congested", "fastest", "default", "shortest"]}
, {"name":"algorithm","alternatives":["dijkstra"]}
, {"name":"vehicle","alternatives":["car", "foot", "bike"]}
]
,
"platforms":[
{
"id":"S6", 
"host":"http://e003m01.istic.univ-rennes1.fr:1536/",
"services":[
{"name":"weighting","alternatives":["fastest", "shortest", "default", "least_congested", "least_polluted"]}
, {"name":"algorithm","alternatives":["dijkstra"]}
, {"name":"vehicle","alternatives":["car", "bike", "foot"]}
]
}
, {
"id":"S47", 
"host":"http://e003m06.istic.univ-rennes1.fr:1537/",
"services":[
{"name":"weighting","alternatives":["fastest", "default", "shortest", "least_congested", "least_polluted"]}
, {"name":"algorithm","alternatives":["dijkstra"]}
, {"name":"vehicle","alternatives":["car", "foot", "bike", "motorcycle"]}
]
}
]
}

