{
"id":"C166", 
"services":[
{"name":"algorithm","alternatives":["astar"]}
, {"name":"vehicle","alternatives":["car", "foot"]}
, {"name":"weighting","alternatives":["fastest", "default"]}
]
,
"platforms":[
{
"id":"S181", 
"host":"http://e008m01.istic.univ-rennes1.fr:1539/",
"services":[
{"name":"algorithm","alternatives":["astar"]}
, {"name":"vehicle","alternatives":["car"]}
, {"name":"weighting","alternatives":["fastest", "shortest"]}
]
}
, {
"id":"S151", 
"host":"http://e103m07.istic.univ-rennes1.fr:15310/",
"services":[
{"name":"algorithm","alternatives":["astar"]}
, {"name":"vehicle","alternatives":["car", "foot", "bike"]}
, {"name":"weighting","alternatives":["fastest", "default", "shortest", "least_congested", "least_noisy"]}
]
}
, {
"id":"S14", 
"host":"http://e003m02.istic.univ-rennes1.fr:1534/",
"services":[
{"name":"algorithm","alternatives":["astar"]}
, {"name":"vehicle","alternatives":["car", "bike"]}
, {"name":"weighting","alternatives":["default", "fastest", "least_noisy", "least_congested", "least_pollen", "most_ozonic", "least_polluted"]}
]
}
, {
"id":"S54", 
"host":"http://e003m07.istic.univ-rennes1.fr:1534/",
"services":[
{"name":"algorithm","alternatives":["astar"]}
, {"name":"vehicle","alternatives":["car", "bike"]}
, {"name":"weighting","alternatives":["default"]}
]
}
]
}

