{
"id":"C889", 
"services":[
{"name":"algorithm","alternatives":["dijkstra"]}
, {"name":"vehicle","alternatives":["car", "bike"]}
, {"name":"weighting","alternatives":["default"]}
]
,
"platforms":[
{
"id":"S53", 
"host":"http://e003m07.istic.univ-rennes1.fr:1533/",
"services":[
{"name":"algorithm","alternatives":["dijkstra"]}
, {"name":"vehicle","alternatives":["car", "bike", "foot"]}
, {"name":"weighting","alternatives":["fastest", "least_congested", "default", "most_scenic"]}
]
}
, {
"id":"S206", 
"host":"http://e008m06.istic.univ-rennes1.fr:1534/",
"services":[
{"name":"algorithm","alternatives":["dijkstra"]}
, {"name":"vehicle","alternatives":["car"]}
, {"name":"weighting","alternatives":["default", "shortest", "least_congested", "fastest"]}
]
}
]
}

