{
"id":"C2557", 
"services":[
{"name":"weighting","alternatives":["default", "least_noisy", "fastest", "most_ozonic", "most_scenic", "least_pollen", "shortest"]}
, {"name":"algorithm","alternatives":["dijkstra"]}
, {"name":"vehicle","alternatives":["car"]}
]
,
"platforms":[
{
"id":"S171", 
"host":"http://e103m08.istic.univ-rennes1.fr:1531/",
"services":[
{"name":"weighting","alternatives":["default", "fastest", "least_pollen", "least_congested"]}
, {"name":"algorithm","alternatives":["dijkstra"]}
, {"name":"vehicle","alternatives":["car"]}
]
}
, {
"id":"S590", 
"host":"http://d022m06.istic.univ-rennes1.fr:1540/",
"services":[
{"name":"weighting","alternatives":["least_congested", "default", "least_polluted", "fastest", "least_noisy"]}
, {"name":"algorithm","alternatives":["dijkstra"]}
, {"name":"vehicle","alternatives":["car"]}
]
}
, {
"id":"S85", 
"host":"http://e003m09.istic.univ-rennes1.fr:1535/",
"services":[
{"name":"weighting","alternatives":["default", "shortest", "fastest", "least_polluted", "least_congested", "least_noisy"]}
, {"name":"algorithm","alternatives":["dijkstra"]}
, {"name":"vehicle","alternatives":["car", "bike"]}
]
}
, {
"id":"S513", 
"host":"http://d020m03.istic.univ-rennes1.fr:1539/",
"services":[
{"name":"weighting","alternatives":["least_noisy", "fastest", "default", "most_ozonic"]}
, {"name":"algorithm","alternatives":["dijkstra"]}
, {"name":"vehicle","alternatives":["car"]}
]
}
, {
"id":"S475", 
"host":"http://e212m10.istic.univ-rennes1.fr:1531/",
"services":[
{"name":"weighting","alternatives":["default", "fastest", "least_pollen", "most_scenic", "shortest"]}
, {"name":"algorithm","alternatives":["dijkstra"]}
, {"name":"vehicle","alternatives":["car"]}
]
}
, {
"id":"S145", 
"host":"http://e103m05.istic.univ-rennes1.fr:1535/",
"services":[
{"name":"weighting","alternatives":["least_noisy", "least_congested", "fastest", "default", "most_ozonic", "shortest", "least_polluted", "least_pollen"]}
, {"name":"algorithm","alternatives":["dijkstra"]}
, {"name":"vehicle","alternatives":["car"]}
]
}
, {
"id":"S137", 
"host":"http://e103m04.istic.univ-rennes1.fr:1537/",
"services":[
{"name":"weighting","alternatives":["least_congested", "default", "least_pollen", "fastest", "shortest", "least_polluted", "least_noisy", "most_ozonic", "most_scenic"]}
, {"name":"algorithm","alternatives":["dijkstra"]}
, {"name":"vehicle","alternatives":["car"]}
]
}
]
}

