{
"id":"C266", 
"services":[
{"name":"weighting","alternatives":["fastest", "default", "least_noisy", "shortest"]}
, {"name":"algorithm","alternatives":["dijkstra"]}
, {"name":"vehicle","alternatives":["car", "foot", "bike"]}
]
,
"platforms":[
{
"id":"S699", 
"host":"http://d026m02.istic.univ-rennes1.fr:1539/",
"services":[
{"name":"weighting","alternatives":["fastest", "shortest", "default", "least_congested", "least_noisy", "most_ozonic", "least_polluted", "most_scenic"]}
, {"name":"algorithm","alternatives":["dijkstra"]}
, {"name":"vehicle","alternatives":["car"]}
]
}
, {
"id":"S82", 
"host":"http://e003m09.istic.univ-rennes1.fr:1532/",
"services":[
{"name":"weighting","alternatives":["least_congested", "fastest", "least_polluted", "default"]}
, {"name":"algorithm","alternatives":["dijkstra"]}
, {"name":"vehicle","alternatives":["car", "foot"]}
]
}
, {
"id":"S169", 
"host":"http://e103m07.istic.univ-rennes1.fr:1539/",
"services":[
{"name":"weighting","alternatives":["fastest", "least_congested", "default", "least_polluted", "least_pollen", "shortest"]}
, {"name":"algorithm","alternatives":["dijkstra"]}
, {"name":"vehicle","alternatives":["foot"]}
]
}
, {
"id":"S128", 
"host":"http://e103m03.istic.univ-rennes1.fr:1538/",
"services":[
{"name":"weighting","alternatives":["shortest", "default"]}
, {"name":"algorithm","alternatives":["dijkstra"]}
, {"name":"vehicle","alternatives":["bike", "car"]}
]
}
, {
"id":"S270", 
"host":"http://e008m08.istic.univ-rennes1.fr:1539/",
"services":[
{"name":"weighting","alternatives":["fastest", "default", "least_congested", "shortest", "least_noisy"]}
, {"name":"algorithm","alternatives":["dijkstra"]}
, {"name":"vehicle","alternatives":["bike", "car"]}
]
}
, {
"id":"S425", 
"host":"http://e212m05.istic.univ-rennes1.fr:1532/",
"services":[
{"name":"weighting","alternatives":["default", "least_congested", "fastest", "shortest"]}
, {"name":"algorithm","alternatives":["dijkstra"]}
, {"name":"vehicle","alternatives":["foot", "car", "bike"]}
]
}
, {
"id":"S786", 
"host":"http://d028m04.istic.univ-rennes1.fr:1534/",
"services":[
{"name":"weighting","alternatives":["fastest", "default", "least_noisy", "least_pollen"]}
, {"name":"algorithm","alternatives":["dijkstra"]}
, {"name":"vehicle","alternatives":["car", "foot"]}
]
}
, {
"id":"S529", 
"host":"http://d020m05.istic.univ-rennes1.fr:1535/",
"services":[
{"name":"weighting","alternatives":["fastest", "shortest", "default", "least_congested", "least_noisy", "least_polluted", "least_pollen"]}
, {"name":"algorithm","alternatives":["dijkstra"]}
, {"name":"vehicle","alternatives":["car", "foot"]}
]
}
, {
"id":"S670", 
"host":"http://d024m08.istic.univ-rennes1.fr:1535/",
"services":[
{"name":"weighting","alternatives":["fastest", "least_noisy", "least_congested", "default", "shortest"]}
, {"name":"algorithm","alternatives":["dijkstra"]}
, {"name":"vehicle","alternatives":["car", "foot", "bike"]}
]
}
]
}

