{
"id":"C3138", 
"services":[
{"name":"weighting","alternatives":["shortest", "default"]}
, {"name":"algorithm","alternatives":["dijkstra"]}
, {"name":"vehicle","alternatives":["car", "bike"]}
]
,
"platforms":[
{
"id":"S95", 
"host":"http://e003m10.istic.univ-rennes1.fr:1535/",
"services":[
{"name":"weighting","alternatives":["least_noisy", "fastest", "least_polluted", "default", "shortest"]}
, {"name":"algorithm","alternatives":["dijkstra"]}
, {"name":"vehicle","alternatives":["car"]}
]
}
, {
"id":"S58", 
"host":"http://e003m06.istic.univ-rennes1.fr:1538/",
"services":[
{"name":"weighting","alternatives":["shortest"]}
, {"name":"algorithm","alternatives":["dijkstra"]}
, {"name":"vehicle","alternatives":["car", "bike", "foot"]}
]
}
, {
"id":"S146", 
"host":"http://e103m05.istic.univ-rennes1.fr:1536/",
"services":[
{"name":"weighting","alternatives":["default"]}
, {"name":"algorithm","alternatives":["dijkstra"]}
, {"name":"vehicle","alternatives":["bike"]}
]
}
, {
"id":"S585", 
"host":"http://d022m06.istic.univ-rennes1.fr:1535/",
"services":[
{"name":"weighting","alternatives":["fastest", "least_congested", "least_polluted", "default", "least_noisy"]}
, {"name":"algorithm","alternatives":["dijkstra"]}
, {"name":"vehicle","alternatives":["car", "bike"]}
]
}
, {
"id":"S689", 
"host":"http://d026m01.istic.univ-rennes1.fr:1534/",
"services":[
{"name":"weighting","alternatives":["least_noisy", "default", "shortest", "fastest"]}
, {"name":"algorithm","alternatives":["dijkstra"]}
, {"name":"vehicle","alternatives":["bike"]}
]
}
, {
"id":"S696", 
"host":"http://d026m02.istic.univ-rennes1.fr:1536/",
"services":[
{"name":"weighting","alternatives":["fastest", "shortest", "default", "least_congested"]}
, {"name":"algorithm","alternatives":["dijkstra"]}
, {"name":"vehicle","alternatives":["car", "bike"]}
]
}
]
}

