{
"id":"C206", 
"services":[
{"name":"weighting","alternatives":["least_congested", "most_ozonic"]}
, {"name":"algorithm","alternatives":["dijkstra"]}
, {"name":"vehicle","alternatives":["foot"]}
]
,
"platforms":[
{
"id":"S48", 
"host":"http://e003m06.istic.univ-rennes1.fr:1538/",
"services":[
{"name":"weighting","alternatives":["fastest", "default", "shortest", "least_congested", "least_polluted", "least_pollen", "most_ozonic"]}
, {"name":"algorithm","alternatives":["dijkstra"]}
, {"name":"vehicle","alternatives":["car", "bike", "foot"]}
]
}
]
}

