{
"id":"C194", 
"services":[
{"name":"weighting","alternatives":["default", "least_polluted", "shortest", "fastest"]}
, {"name":"algorithm","alternatives":["dijkstra"]}
, {"name":"vehicle","alternatives":["scooter", "car"]}
]
,
"platforms":[
{
"id":"S37", 
"host":"http://e003m05.istic.univ-rennes1.fr:1537/",
"services":[
{"name":"weighting","alternatives":["least_polluted", "fastest", "default", "shortest", "most_scenic", "least_noisy"]}
, {"name":"algorithm","alternatives":["dijkstra"]}
, {"name":"vehicle","alternatives":["car", "foot", "scooter", "motorcycle"]}
]
}
, {
"id":"S5", 
"host":"http://e003m01.istic.univ-rennes1.fr:1535/",
"services":[
{"name":"weighting","alternatives":["fastest", "least_polluted", "least_pollen", "default", "least_noisy", "shortest", "least_congested", "most_ozonic"]}
, {"name":"algorithm","alternatives":["dijkstra"]}
, {"name":"vehicle","alternatives":["car", "foot", "bike"]}
]
}
, {
"id":"S45", 
"host":"http://e003m06.istic.univ-rennes1.fr:1535/",
"services":[
{"name":"weighting","alternatives":["shortest", "fastest", "default", "least_congested", "most_scenic", "least_noisy", "least_polluted", "least_pollen"]}
, {"name":"algorithm","alternatives":["dijkstra"]}
, {"name":"vehicle","alternatives":["foot", "car", "motorcycle", "bike", "scooter"]}
]
}
]
}

