{
"id":"C851", 
"services":[
{"name":"algorithm","alternatives":["astar"]}
, {"name":"vehicle","alternatives":["car", "bike", "foot"]}
, {"name":"weighting","alternatives":["default"]}
]
,
"platforms":[
{
"id":"S14", 
"host":"http://e003m02.istic.univ-rennes1.fr:1534/",
"services":[
{"name":"algorithm","alternatives":["astar"]}
, {"name":"vehicle","alternatives":["car", "bike", "foot"]}
, {"name":"weighting","alternatives":["default", "fastest", "least_noisy", "most_ozonic", "least_polluted", "shortest"]}
]
}
, {
"id":"S21", 
"host":"http://e003m04.istic.univ-rennes1.fr:1531/",
"services":[
{"name":"algorithm","alternatives":["astar"]}
, {"name":"vehicle","alternatives":["car", "foot"]}
, {"name":"weighting","alternatives":["default"]}
]
}
]
}

