{
"id":"C3175", 
"services":[
{"name":"algorithm","alternatives":["dijkstra"]}
, {"name":"vehicle","alternatives":["car", "bike"]}
, {"name":"weighting","alternatives":["default"]}
]
,
"platforms":[
{
"id":"S73", 
"host":"http://e003m08.istic.univ-rennes1.fr:1533/",
"services":[
{"name":"algorithm","alternatives":["dijkstra"]}
, {"name":"vehicle","alternatives":["car", "bike", "motorcycle", "foot", "scooter"]}
, {"name":"weighting","alternatives":["least_congested", "default", "fastest", "most_ozonic"]}
]
}
]
}

