{
"id":"C3118", 
"services":[
{"name":"algorithm","alternatives":["dijkstra"]}
, {"name":"vehicle","alternatives":["car"]}
, {"name":"weighting","alternatives":["fastest", "shortest", "default", "least_congested"]}
]
,
"platforms":[
{
"id":"S752", 
"host":"http://d026m08.istic.univ-rennes1.fr:1535/",
"services":[
{"name":"algorithm","alternatives":["dijkstra"]}
, {"name":"vehicle","alternatives":["bike", "car", "foot"]}
, {"name":"weighting","alternatives":["default", "fastest", "shortest", "least_polluted", "least_congested"]}
]
}
, {
"id":"S374", 
"host":"http://e105m08.istic.univ-rennes1.fr:1538/",
"services":[
{"name":"algorithm","alternatives":["dijkstra"]}
, {"name":"vehicle","alternatives":["car", "scooter", "foot", "bike"]}
, {"name":"weighting","alternatives":["least_congested", "fastest", "least_pollen", "default", "most_scenic", "most_ozonic", "least_noisy"]}
]
}
, {
"id":"S540", 
"host":"http://d020m07.istic.univ-rennes1.fr:1534/",
"services":[
{"name":"algorithm","alternatives":["dijkstra"]}
, {"name":"vehicle","alternatives":["car", "foot"]}
, {"name":"weighting","alternatives":["default", "most_scenic"]}
]
}
, {
"id":"S134", 
"host":"http://e103m04.istic.univ-rennes1.fr:1534/",
"services":[
{"name":"algorithm","alternatives":["dijkstra"]}
, {"name":"vehicle","alternatives":["car", "motorcycle"]}
, {"name":"weighting","alternatives":["fastest", "least_congested", "shortest"]}
]
}
]
}

