{
"id":"C116", 
"services":[
{"name":"algorithm","alternatives":["dijkstra"]}
, {"name":"vehicle","alternatives":["car", "bike", "foot"]}
, {"name":"weighting","alternatives":["fastest"]}
]
,
"platforms":[
{
"id":"S5", 
"host":"http://e003m01.istic.univ-rennes1.fr:1535/",
"services":[
{"name":"algorithm","alternatives":["dijkstra"]}
, {"name":"vehicle","alternatives":["car", "bike", "foot", "motorcycle"]}
, {"name":"weighting","alternatives":["default", "fastest", "shortest", "least_polluted", "least_noisy"]}
]
}
, {
"id":"S18", 
"host":"http://e003m02.istic.univ-rennes1.fr:1537/",
"services":[
{"name":"algorithm","alternatives":["dijkstra"]}
, {"name":"vehicle","alternatives":["car", "motorcycle", "bike"]}
, {"name":"weighting","alternatives":["default", "fastest", "least_polluted", "shortest", "least_congested", "most_ozonic"]}
]
}
]
}

