{
"id":"C209", 
"services":[
{"name":"weighting","alternatives":["default", "least_noisy"]}
, {"name":"algorithm","alternatives":["dijkstra"]}
, {"name":"vehicle","alternatives":["car"]}
]
,
"platforms":[
{
"id":"S47", 
"host":"http://e003m06.istic.univ-rennes1.fr:1535/",
"services":[
{"name":"weighting","alternatives":["default", "fastest", "least_noisy"]}
, {"name":"algorithm","alternatives":["dijkstra"]}
, {"name":"vehicle","alternatives":["car", "motorcycle", "bike"]}
]
}
, {
"id":"S49", 
"host":"http://e003m06.istic.univ-rennes1.fr:1537/",
"services":[
{"name":"weighting","alternatives":["fastest", "default", "shortest", "least_noisy", "least_polluted", "most_ozonic"]}
, {"name":"algorithm","alternatives":["dijkstra"]}
, {"name":"vehicle","alternatives":["car", "foot", "motorcycle", "bike"]}
]
}
]
}

