{
"id":"C2034", 
"services":[
{"name":"algorithm","alternatives":["dijkstra"]}
, {"name":"vehicle","alternatives":["bike", "car"]}
, {"name":"weighting","alternatives":["shortest", "default", "fastest"]}
]
,
"platforms":[
{
"id":"S832", 
"host":"http://d028m09.istic.univ-rennes1.fr:1540/",
"services":[
{"name":"algorithm","alternatives":["dijkstra"]}
, {"name":"vehicle","alternatives":["car", "bike"]}
, {"name":"weighting","alternatives":["default", "fastest", "shortest", "least_noisy", "least_polluted", "least_congested"]}
]
}
, {
"id":"S796", 
"host":"http://d028m05.istic.univ-rennes1.fr:1534/",
"services":[
{"name":"algorithm","alternatives":["dijkstra"]}
, {"name":"vehicle","alternatives":["car", "bike"]}
, {"name":"weighting","alternatives":["fastest", "default", "shortest", "least_congested", "least_polluted", "least_noisy", "most_ozonic"]}
]
}
, {
"id":"S72", 
"host":"http://e003m08.istic.univ-rennes1.fr:1532/",
"services":[
{"name":"algorithm","alternatives":["dijkstra"]}
, {"name":"vehicle","alternatives":["car", "bike", "motorcycle", "foot"]}
, {"name":"weighting","alternatives":["fastest", "least_noisy", "shortest", "default", "least_congested"]}
]
}
, {
"id":"S536", 
"host":"http://d020m06.istic.univ-rennes1.fr:1535/",
"services":[
{"name":"algorithm","alternatives":["dijkstra"]}
, {"name":"vehicle","alternatives":["car", "foot", "bike"]}
, {"name":"weighting","alternatives":["default", "fastest", "least_congested", "shortest"]}
]
}
]
}

