{
"id":"C478", 
"services":[
{"name":"vehicle","alternatives":["car"]}
, {"name":"weighting","alternatives":["fastest", "least_polluted", "least_noisy"]}
, {"name":"algorithm","alternatives":["dijkstra"]}
]
,
"platforms":[
{
"id":"S525", 
"host":"http://d022m07.istic.univ-rennes1.fr:1535/",
"services":[
{"name":"vehicle","alternatives":["car", "bike", "foot"]}
, {"name":"weighting","alternatives":["shortest", "fastest", "least_congested", "default", "least_noisy", "least_polluted"]}
, {"name":"algorithm","alternatives":["dijkstra"]}
]
}
, {
"id":"S542", 
"host":"http://d022m10.istic.univ-rennes1.fr:1532/",
"services":[
{"name":"vehicle","alternatives":["car"]}
, {"name":"weighting","alternatives":["default", "least_polluted", "fastest"]}
, {"name":"algorithm","alternatives":["dijkstra"]}
]
}
]
}

