{
"id":"C89", 
"services":[
{"name":"algorithm","alternatives":["diksjtra"]}
, {"name":"weighting","alternatives":["fastest"]}
, {"name":"vehicle","alternatives":["bike", "car"]}
]
,
"platforms":[
{
"id":"S301", 
"host":"http://e105m06.istic.univ-rennes1.fr:1531/",
"services":[
{"name":"algorithm","alternatives":["diksjtra"]}
, {"name":"weighting","alternatives":["fastest", "default", "least_pollen", "shortest"]}
, {"name":"vehicle","alternatives":["car"]}
]
}
, {
"id":"S626", 
"host":"http://d026m04.istic.univ-rennes1.fr:1533/",
"services":[
{"name":"algorithm","alternatives":["diksjtra"]}
, {"name":"weighting","alternatives":["default", "fastest", "least_polluted", "least_noisy", "least_congested", "shortest", "least_pollen"]}
, {"name":"vehicle","alternatives":["car", "bike"]}
]
}
]
}

