{
"id":"C2185", 
"services":[
{"name":"algorithm","alternatives":["astar"]}
, {"name":"weighting","alternatives":["fastest", "least_noisy"]}
, {"name":"vehicle","alternatives":["car"]}
]
,
"platforms":[
{
"id":"S110", 
"host":"http://e103m02.istic.univ-rennes1.fr:15310/",
"services":[
{"name":"algorithm","alternatives":["astar"]}
, {"name":"weighting","alternatives":["fastest", "shortest", "default", "least_polluted"]}
, {"name":"vehicle","alternatives":["car"]}
]
}
, {
"id":"S358", 
"host":"http://e212m01.istic.univ-rennes1.fr:1538/",
"services":[
{"name":"algorithm","alternatives":["astar"]}
, {"name":"weighting","alternatives":["least_noisy", "shortest", "fastest"]}
, {"name":"vehicle","alternatives":["car", "foot"]}
]
}
]
}

