{
"id":"C3461", 
"services":[
{"name":"algorithm","alternatives":["diksjtra"]}
, {"name":"weighting","alternatives":["least_polluted", "default", "fastest"]}
, {"name":"vehicle","alternatives":["bike"]}
]
,
"platforms":[
{
"id":"S504", 
"host":"http://d022m04.istic.univ-rennes1.fr:1534/",
"services":[
{"name":"algorithm","alternatives":["diksjtra"]}
, {"name":"weighting","alternatives":["least_polluted", "default", "most_ozonic", "least_congested"]}
, {"name":"vehicle","alternatives":["bike"]}
]
}
, {
"id":"S738", 
"host":"http://d122m02.istic.univ-rennes1.fr:1535/",
"services":[
{"name":"algorithm","alternatives":["diksjtra"]}
, {"name":"weighting","alternatives":["default", "most_ozonic", "least_congested", "fastest", "least_polluted", "shortest", "least_noisy"]}
, {"name":"vehicle","alternatives":["bike"]}
]
}
]
}

