{
"id":"C1975", 
"services":[
{"name":"algorithm","alternatives":["dijkstra"]}
, {"name":"vehicle","alternatives":["foot"]}
, {"name":"weighting","alternatives":["least_polluted", "default"]}
]
,
"platforms":[
{
"id":"S541", 
"host":"http://d020m07.istic.univ-rennes1.fr:1535/",
"services":[
{"name":"algorithm","alternatives":["dijkstra"]}
, {"name":"vehicle","alternatives":["car", "foot"]}
, {"name":"weighting","alternatives":["least_congested", "fastest", "least_polluted"]}
]
}
, {
"id":"S636", 
"host":"http://d024m01.istic.univ-rennes1.fr:1540/",
"services":[
{"name":"algorithm","alternatives":["dijkstra"]}
, {"name":"vehicle","alternatives":["car", "foot"]}
, {"name":"weighting","alternatives":["default", "fastest", "least_polluted"]}
]
}
]
}

